augmentsNight/__init__.py
augmentsNight/augmentsNight.py
augmentsNight-1.0.dist-info/LICENSE
augmentsNight-1.0.dist-info/METADATA
augmentsNight-1.0.dist-info/WHEEL
augmentsNight-1.0.dist-info/top_level.txt
augmentsNight-1.0.dist-info/RECORD
