Metadata-Version: 2.1
Name: augmentsNight
Version: 1.0
Summary: 啦啦啦
Home-page: UNKNOWN
Author: xinian_night
Author-email: 1912681536@qq.com
License: UNKNOWN
Platform: UNKNOWN
Classifier: Programming Language :: Python :: 3
Classifier: License :: OSI Approved :: MIT License
Classifier: Operating System :: OS Independent
Requires-Python: >=3
License-File: LICENSE
Requires-Dist: opencv-python
Requires-Dist: numpy
